olclient/__init__.py
olclient/bots.py
olclient/cli.py
olclient/common.py
olclient/config.py
olclient/marc.py
olclient/openlibrary.py
olclient/utils.py
olclient/schemata/author.schema.json
olclient/schemata/edition.schema.json
olclient/schemata/shared_definitions.json
olclient/schemata/work.schema.json
openlibrary_client_mek-0.0.30.dist-info/LICENSE
openlibrary_client_mek-0.0.30.dist-info/METADATA
openlibrary_client_mek-0.0.30.dist-info/WHEEL
openlibrary_client_mek-0.0.30.dist-info/entry_points.txt
openlibrary_client_mek-0.0.30.dist-info/top_level.txt
openlibrary_client_mek-0.0.30.dist-info/RECORD
