Metadata-Version: 2.1
Name: openlibrary-client-mek
Version: 0.0.30
Summary: A python client for Open Library
Home-page: https://github.com/internetarchive/openlibrary-client
Author: Internet Archive
Author-email: mek@archive.org
License: LICENSE
Platform: any
Classifier: Development Status :: 2 - Pre-Alpha
Classifier: Intended Audience :: Developers
Classifier: License :: OSI Approved :: GNU Affero General Public License v3
Classifier: Topic :: Software Development :: Build Tools
Classifier: Topic :: Software Development :: Libraries
Classifier: Programming Language :: Python
Classifier: Programming Language :: Python :: 3
Classifier: Programming Language :: Python :: 3.7
Classifier: Programming Language :: Python :: 3.8
Requires-Dist: backoff (==1.10.0)
Requires-Dist: internetarchive (==1.9.0)
Requires-Dist: jsonpickle (==0.9.3)
Requires-Dist: jsonschema (==3.2.0)
Requires-Dist: pymarc (==3.2.0)
Requires-Dist: requests[security] (==2.23.0)
Requires-Dist: simplejson (==3.16)
Requires-Dist: six (==1.14.0)
